<neat_id_map>
<neuron_id_map>
</neuron_id_map>
<connection_id_map>
<connection id="64" src_neuron_id="0" dest_neuron_id="63" /><connection id="30" src_neuron_id="14" dest_neuron_id="15" /><connection id="61" src_neuron_id="13" dest_neuron_id="47" /><connection id="92" src_neuron_id="12" dest_neuron_id="79" /><connection id="26" src_neuron_id="10" dest_neuron_id="15" /><connection id="57" src_neuron_id="9" dest_neuron_id="47" /><connection id="88" src_neuron_id="8" dest_neuron_id="79" /><connection id="22" src_neuron_id="6" dest_neuron_id="15" /><connection id="53" src_neuron_id="5" dest_neuron_id="47" /><connection id="84" src_neuron_id="4" dest_neuron_id="79" /><connection id="18" src_neuron_id="2" dest_neuron_id="15" /><connection id="49" src_neuron_id="1" dest_neuron_id="47" /><connection id="80" src_neuron_id="0" dest_neuron_id="79" /><connection id="46" src_neuron_id="14" dest_neuron_id="31" /><connection id="77" src_neuron_id="13" dest_neuron_id="63" /><connection id="108" src_neuron_id="12" dest_neuron_id="95" /><connection id="42" src_neuron_id="10" dest_neuron_id="31" /><connection id="73" src_neuron_id="9" dest_neuron_id="63" /><connection id="104" src_neuron_id="8" dest_neuron_id="95" /><connection id="38" src_neuron_id="6" dest_neuron_id="31" /><connection id="69" src_neuron_id="5" dest_neuron_id="63" /><connection id="100" src_neuron_id="4" dest_neuron_id="95" /><connection id="34" src_neuron_id="2" dest_neuron_id="31" /><connection id="65" src_neuron_id="1" dest_neuron_id="63" /><connection id="96" src_neuron_id="0" dest_neuron_id="95" /><connection id="62" src_neuron_id="14" dest_neuron_id="47" /><connection id="93" src_neuron_id="13" dest_neuron_id="79" /><connection id="27" src_neuron_id="11" dest_neuron_id="15" /><connection id="58" src_neuron_id="10" dest_neuron_id="47" /><connection id="89" src_neuron_id="9" dest_neuron_id="79" /><connection id="23" src_neuron_id="7" dest_neuron_id="15" /><connection id="54" src_neuron_id="6" dest_neuron_id="47" /><connection id="85" src_neuron_id="5" dest_neuron_id="79" /><connection id="19" src_neuron_id="3" dest_neuron_id="15" /><connection id="50" src_neuron_id="2" dest_neuron_id="47" /><connection id="81" src_neuron_id="1" dest_neuron_id="79" /><connection id="78" src_neuron_id="14" dest_neuron_id="63" /><connection id="109" src_neuron_id="13" dest_neuron_id="95" /><connection id="43" src_neuron_id="11" dest_neuron_id="31" /><connection id="74" src_neuron_id="10" dest_neuron_id="63" /><connection id="105" src_neuron_id="9" dest_neuron_id="95" /><connection id="39" src_neuron_id="7" dest_neuron_id="31" /><connection id="70" src_neuron_id="6" dest_neuron_id="63" /><connection id="101" src_neuron_id="5" dest_neuron_id="95" /><connection id="35" src_neuron_id="3" dest_neuron_id="31" /><connection id="66" src_neuron_id="2" dest_neuron_id="63" /><connection id="97" src_neuron_id="1" dest_neuron_id="95" /><connection id="94" src_neuron_id="14" dest_neuron_id="79" /><connection id="28" src_neuron_id="12" dest_neuron_id="15" /><connection id="59" src_neuron_id="11" dest_neuron_id="47" /><connection id="90" src_neuron_id="10" dest_neuron_id="79" /><connection id="24" src_neuron_id="8" dest_neuron_id="15" /><connection id="55" src_neuron_id="7" dest_neuron_id="47" /><connection id="86" src_neuron_id="6" dest_neuron_id="79" /><connection id="20" src_neuron_id="4" dest_neuron_id="15" /><connection id="51" src_neuron_id="3" dest_neuron_id="47" /><connection id="82" src_neuron_id="2" dest_neuron_id="79" /><connection id="16" src_neuron_id="0" dest_neuron_id="15" /><connection id="110" src_neuron_id="14" dest_neuron_id="95" /><connection id="44" src_neuron_id="12" dest_neuron_id="31" /><connection id="75" src_neuron_id="11" dest_neuron_id="63" /><connection id="106" src_neuron_id="10" dest_neuron_id="95" /><connection id="40" src_neuron_id="8" dest_neuron_id="31" /><connection id="71" src_neuron_id="7" dest_neuron_id="63" /><connection id="102" src_neuron_id="6" dest_neuron_id="95" /><connection id="36" src_neuron_id="4" dest_neuron_id="31" /><connection id="67" src_neuron_id="3" dest_neuron_id="63" /><connection id="98" src_neuron_id="2" dest_neuron_id="95" /><connection id="32" src_neuron_id="0" dest_neuron_id="31" /><connection id="29" src_neuron_id="13" dest_neuron_id="15" /><connection id="60" src_neuron_id="12" dest_neuron_id="47" /><connection id="91" src_neuron_id="11" dest_neuron_id="79" /><connection id="25" src_neuron_id="9" dest_neuron_id="15" /><connection id="56" src_neuron_id="8" dest_neuron_id="47" /><connection id="87" src_neuron_id="7" dest_neuron_id="79" /><connection id="21" src_neuron_id="5" dest_neuron_id="15" /><connection id="52" src_neuron_id="4" dest_neuron_id="47" /><connection id="83" src_neuron_id="3" dest_neuron_id="79" /><connection id="17" src_neuron_id="1" dest_neuron_id="15" /><connection id="48" src_neuron_id="0" dest_neuron_id="47" /><connection id="45" src_neuron_id="13" dest_neuron_id="31" /><connection id="76" src_neuron_id="12" dest_neuron_id="63" /><connection id="107" src_neuron_id="11" dest_neuron_id="95" /><connection id="41" src_neuron_id="9" dest_neuron_id="31" /><connection id="72" src_neuron_id="8" dest_neuron_id="63" /><connection id="103" src_neuron_id="7" dest_neuron_id="95" /><connection id="37" src_neuron_id="5" dest_neuron_id="31" /><connection id="68" src_neuron_id="4" dest_neuron_id="63" /><connection id="99" src_neuron_id="3" dest_neuron_id="95" /><connection id="33" src_neuron_id="1" dest_neuron_id="31" /></connection_id_map>
</neat_id_map>
